journal/__init__.py
journal/cli.py
journal/version.py
journal/commands/__init__.py
journal/commands/append.py
journal/commands/end.py
journal/commands/version.py
journalists/__init__.py
journalists/cli.py
journalists/version.py
journalists/commands/__init__.py
journalists/commands/append.py
journalists/commands/end.py
journalists/commands/version.py
journalists-0.0.2.dist-info/LICENSE
journalists-0.0.2.dist-info/METADATA
journalists-0.0.2.dist-info/WHEEL
journalists-0.0.2.dist-info/entry_points.txt
journalists-0.0.2.dist-info/top_level.txt
journalists-0.0.2.dist-info/RECORD
