Metadata-Version: 2.1
Name: journalists
Version: 0.0.2
Summary: App for writing fun daily journalists.
Home-page: https://github.com/ashkan18/journal
Author: Ashkan Nasseri
Author-email: ashkan18@gmail.com
License: UNKNOWN
Platform: UNKNOWN
Classifier: Programming Language :: Python :: 3
Classifier: License :: OSI Approved :: MIT License
Classifier: Operating System :: OS Independent
Requires-Python: >=3.6
Requires-Dist: click (~=6.7)
Requires-Dist: prompt-toolkit (~=1.0.15)
Requires-Dist: termcolor (~=1.1)
